snark_bot/__init__.py
snark_bot/__main__.py
snark_bot/bot.py
snark_bot-0.1.0.dist-info/LICENSE
snark_bot-0.1.0.dist-info/WHEEL
snark_bot-0.1.0.dist-info/METADATA
snark_bot-0.1.0.dist-info/RECORD
